batteryopt/__init__.py
batteryopt/cli.py
batteryopt/core.py
batteryopt/pyomoio.py
tests/__init__.py
tests/test_cli.py
tests/test_core.py
batteryopt-0.1.0.dist-info/METADATA
batteryopt-0.1.0.dist-info/WHEEL
batteryopt-0.1.0.dist-info/entry_points.txt
batteryopt-0.1.0.dist-info/top_level.txt
batteryopt-0.1.0.dist-info/RECORD
